pydove/__init__.py
pydove/color.py
pydove/figure_manager.py
pydove/plot.py
pydove/regplot.py
pydove-0.3.5.dist-info/LICENSE
pydove-0.3.5.dist-info/METADATA
pydove-0.3.5.dist-info/WHEEL
pydove-0.3.5.dist-info/top_level.txt
pydove-0.3.5.dist-info/RECORD
