Metadata-Version: 2.1
Name: pydove
Version: 0.3.5
Summary: An assortment of graphics utilities
Home-page: https://github.com/ttesileanu/pydove
Author: Tiberiu Tesileanu
Author-email: ttesileanu@gmail.com
License: MIT
Platform: UNKNOWN
Classifier: License :: OSI Approved :: MIT License
Classifier: Programming Language :: Python :: 3
Classifier: Programming Language :: Python :: 3.6
Classifier: Intended Audience :: Science/Research
Classifier: Topic :: Scientific/Engineering :: Visualization
Requires-Dist: setuptools
Requires-Dist: statsmodels
Requires-Dist: matplotlib (>=3.1.1)
Requires-Dist: seaborn
Requires-Dist: numpy (>=1.16.4)
Requires-Dist: scipy
